{
    "cards": [
      {
        "id": 1,
        "control": false,
        "type": "Agile",
        "points": 1
      },
      {
        "id": 1,
        "control": true,
        "type": "Mean",
        "points": 3
      },
      {
        "id": 2,
        "control": true,
        "type": "Agile",
        "points": 1
      },
      {
        "id": 2,
        "control": false,
        "type": "Powerful",
        "points": "d6"
      },
      {
        "id": 3,
        "control": true,
        "type": "Agile",
        "points": 2
      },
      {
        "id": 3,
        "control": false,
        "type": "Quick",
        "points": 2
      },
      {
        "id": 4,
        "control": false,
        "type": "Agile",
        "points": 2
      },
      {
        "id": 4,
        "control": true,
        "type": "Strong",
        "points": 2
      },
      {
        "id": 5,
        "control": false,
        "type": "Wild Card",
        "text": "Go to appropriate WILD CARD chart in game book and roll dice for result!"
      },
      {
        "id": 5,
        "control": false,
        "type": "Agile",
        "points": 3
      },
      {
        "id": 6,
        "control": false,
        "type": "Agile",
        "points": 3
      },
      {
        "id": 6,
        "control": false,
        "type": "Quick",
        "points": 1
      },
      {
        "id": 7,
        "control": true,
        "type": "Cheat",
        "points": 1
      },
      {
        "id": 7,
        "control": false,
        "type": "Quick",
        "points": 3
      },
      {
        "id": 8,
        "control": false,
        "type": "TV",
        "points": {
          "AAA": 5,
          "AA": 4,
          "A": 3,
          "B": 2,
          "C": 1,
          "D": 1,
          "E": 0
        }
      },
      {
        "id": 8,
        "control": false,
        "type": "Cheat",
        "points": 1
      },
      {
        "id": 9,
        "control": false,
        "type": "Wild Card",
        "text": "Go to appropriate WILD CARD chart in game book and roll dice for result!"
      },
      {
        "id": 9,
        "control": false,
        "type": "Cheat",
        "points": 2
      },
      {
        "id": 10,
        "control": false,
        "type": "Cheat",
        "points": 2
      },
      {
        "id": 10,
        "control": true,
        "type": "Powerful",
        "points": 2
      },
      {
        "id": 11,
        "control": true,
        "type": "Cheat",
        "points": 3
      },
      {
        "id": 11,
        "control": false,
        "type": "Quick",
        "points": 1
      },
      {
        "id": 12,
        "control": false,
        "type": "Cheat",
        "points": 3
      },
      {
        "id": 12,
        "control": true,
        "type": "Strong",
        "points": 1
      },
      {
        "id": 13,
        "control": false,
        "type": "TV",
        "points": {
          "AAA": 4,
          "AA": 3,
          "A": 2,
          "B": 2,
          "C": 0,
          "D": 0,
          "E": 0
        }
      },
      {
        "id": 13,
        "control": false,
        "type": "Cheat",
        "points": "d6"
      },
      {
        "id": 14,
        "control": false,
        "type": "Favorite",
        "points": 2
      },
      {
        "id": 14,
        "control": true,
        "type": "Smart",
        "points": 2
      },
      {
        "id": 15,
        "control": false,
        "type": "Favorite",
        "points": 2
      },
      {
        "id": 15,
        "control": false,
        "type": "Object",
        "points": 2
      },
      {
        "id": 16,
        "control": true,
        "type": "Favorite",
        "points": 3
      },
      {
        "id": 16,
        "control": false,
        "type": "Strong",
        "points": 1
      },
      {
        "id": 17,
        "control": false,
        "type": "TV",
        "points": {
          "AAA": 5,
          "AA": 4,
          "A": 3,
          "B": 2,
          "C": 1,
          "D": 0,
          "E": 0
        }
      },
      {
        "id": 17,
        "control": false,
        "type": "Favorite",
        "points": 3
      },
      {
        "id": 18,
        "control": false,
        "type": "Wild Card",
        "text": "Go to appropriate WILD CARD chart in game book and roll dice for result!"
      },
      {
        "id": 18,
        "control": false,
        "type": "Favorite",
        "points": "d6"
      },
      {
        "id": 19,
        "control": false,
        "type": "Favorite",
        "points": "d6"
      },
      {
        "id": 19,
        "control": true,
        "type": "Object",
        "points": 1
      },
      {
        "id": 20,
        "control": false,
        "type": "TV",
        "points": {
          "AAA": 5,
          "AA": 4,
          "A": 3,
          "B": 2,
          "C": 1,
          "D": 1,
          "E": 0
        }
      },
      {
        "id": 20,
        "control": false,
        "type": "Favorite",
        "points": "d6"
      },
      {
        "id": 21,
        "control": false,
        "type": "Grudge",
        "points": 1
      },
      {
        "id": 21,
        "control": false,
        "type": "Quick",
        "points": 3
      },
      {
        "id": 22,
        "control": false,
        "type": "Grudge",
        "points": 1
      },
      {
        "id": 22,
        "control": false,
        "type": "Smart",
        "points": 3
      },
      {
        "id": 23,
        "control": false,
        "type": "TV",
        "points": {
          "AAA": 5,
          "AA": 4,
          "A": 3,
          "B": 2,
          "C": 1,
          "D": 0,
          "E": 0
        }
      },
      {
        "id": 23,
        "control": false,
        "type": "Grudge",
        "points": 1
      },
      {
        "id": 24,
        "control": true,
        "type": "Specialty",
        "text": "Check wrestler's card."
      },
      {
        "id": 24,
        "control": false,
        "type": "Grudge",
        "points": 2
      },
      {
        "id": 25,
        "control": true,
        "type": "Signature",
        "points": "d6",
        "text": "If wrestler scored on last fact-action card."
      },
      {
        "id": 25,
        "control": false,
        "type": "Grudge",
        "points": 2
      },
      {
        "id": 26,
        "control": false,
        "type": "Grudge",
        "points": 2
      },
      {
        "id": 26,
        "control": false,
        "type": "Powerful",
        "points": "d6"
      },
      {
        "id": 27,
        "control": false,
        "type": "Specialty",
        "text": "Check wrestler's card."
      },
      {
        "id": 27,
        "control": true,
        "type": "Smart",
        "points": 2
      },
      {
        "id": 28,
        "control": false,
        "type": "TV",
        "points": {
          "AAA": 5,
          "AA": 4,
          "A": 3,
          "B": 2,
          "C": 1,
          "D": 1,
          "E": 0
        }
      },
      {
        "id": 28,
        "control": false,
        "type": "Grudge",
        "points": 3
      },
      {
        "id": 29,
        "control": false,
        "type": "Wild Card",
        "text": "Go to the appropriate WILD CARD chart in the game book and roll dice for results!"
      },
      {
        "id": 29,
        "control": false,
        "type": "Grudge",
        "points": 3
      },
      {
        "id": 30,
        "control": true,
        "type": "Heavy",
        "points": 1
      },
      {
        "id": 30,
        "control": false,
        "type": "Object",
        "points": 3
      },
      {
        "id": 31,
        "control": false,
        "type": "Heavy",
        "points": 1
      },
      {
        "id": 31,
        "control": false,
        "type": "Strong",
        "points": 3
      },
      {
        "id": 32,
        "control": false,
        "type": "Heavy",
        "points": 2
      },
      {
        "id": 32,
        "control": true,
        "type": "Quick",
        "points": 2
      },
      {
        "id": 33,
        "control": true,
        "type": "Heavy",
        "points": 2
      },
      {
        "id": 33,
        "control": false,
        "type": "Smart",
        "points": 2
      },
      {
        "id": 34,
        "control": false,
        "type": "Heavy",
        "points": 3
      },
      {
        "id": 34,
        "control": false,
        "type": "Powerful",
        "points": "d6"
      },
      {
        "id": 35,
        "control": false,
        "type": "TV",
        "points": {
          "AAA": 5,
          "AA": 4,
          "A": 3,
          "B": 2,
          "C": 1,
          "D": 1,
          "E": 0
        }
      },
      {
        "id": 35,
        "control": false,
        "type": "Heavy",
        "points": 3
      },
      {
        "id": 36,
        "control": true,
        "type": "Helped",
        "points": 3
      },
      {
        "id": 36,
        "control": false,
        "type": "Powerful",
        "points": 3
      },
      {
        "id": 37,
        "control": true,
        "type": "Helped",
        "points": 2
      },
      {
        "id": 37,
        "control": false,
        "type": "Smart",
        "points": 3
      },
      {
        "id": 38,
        "control": false,
        "type": "Helped",
        "text": "Go to HIGHLIGHT REEL \"G\", \"M\" or \"V\" depending on the source of help."
      },
      {
        "id": 38,
        "control": false,
        "type": "Strong",
        "points": 3
      },
      {
        "id": 39,
        "control": false,
        "type": "Wild Card",
        "text": "Go to appropriate WILD CARD chart in game book and roll dice for result!"
      },
      {
        "id": 39,
        "control": false,
        "type": "Helped",
        "text": "Go to HIGHLIGHT REEL \"G\", \"M\" or \"V\" depending on the source of help."
      },
      {
        "id": 40,
        "control": false,
        "type": "Helped",
        "text": "Go to HIGHLIGHT REEL \"G\", \"M\" or \"V\" depending on the source of help."
      },
      {
        "id": 40,
        "control": true,
        "type": "Signature",
        "points": "d6",
        "text": "If wrestler scored on last fact-action card."
      },
      {
        "id": 41,
        "control": false,
        "type": "TV",
        "points": {
          "AAA": 5,
          "AA": 4,
          "A": 3,
          "B": 2,
          "C": 1,
          "D": 0,
          "E": 0
        }
      },
      {
        "id": 41,
        "control": false,
        "type": "Helped",
        "text": "Go to HIGHLIGHT REEL \"G\", \"M\" or \"V\" depending on the source of help."
      },
      {
        "id": 42,
        "control": false,
        "type": "Highlight Reel",
        "text": "Roll again, A or B."
      },
      {
        "id": 42,
        "control": false,
        "type": "Smart",
        "points": 1
      },
      {
        "id": 43,
        "control": true,
        "type": "Specialty",
        "text": "Check wrestler's card."
      },
      {
        "id": 43,
        "control": false,
        "type": "Highlight Reel",
        "text": "Roll again, A or B."
      },
      {
        "id": 44,
        "control": false,
        "type": "Mean",
        "points": 1
      },
      {
        "id": 44,
        "control": true,
        "type": "Powerful",
        "points": 3
      },
      {
        "id": 45,
        "control": true,
        "type": "Mean",
        "points": 1
      },
      {
        "id": 45,
        "control": false,
        "type": "Strong",
        "points": 3
      },
      {
        "id": 46,
        "control": false,
        "type": "Wild Card",
        "text": "Go to appropriate WILD CARD chart in game book and roll dice for result!"
      },
      {
        "id": 46,
        "control": false,
        "type": "Mean",
        "points": 2
      },
      {
        "id": 46,
        "control": false,
        "type": "Mean",
        "points": 2
      },
      {
        "id": 47,
        "control": false,
        "type": "TV",
        "points": {
          "AAA": 5,
          "AA": 4,
          "A": 3,
          "B": 2,
          "C": 1,
          "D": 0,
          "E": 0
        }
      },
      {
        "id": 47,
        "control": false,
        "type": "Mean",
        "points": 2
      },
      {
        "id": 48,
        "control": false,
        "type": "Mean",
        "points": 3
      },
      {
        "id": 48,
        "control": false,
        "type": "Smart",
        "points": 1
      },
      {
        "id": 49,
        "control": true,
        "type": "Favorite",
        "points": 2
      },
      {
        "id": 49,
        "control": false,
        "type": "Helped",
        "points": 3
      },
      {
        "id": 50,
        "control": false,
        "type": "Mean",
        "points": 2
      },
      {
        "id": 50,
        "control": true,
        "type": "Title Holder",
        "points": "d6"
      },
      {
        "id": 51,
        "control": false,
        "type": "Specialty",
        "text": "Check wrestler's card."
      },
      {
        "id": 51,
        "control": true,
        "type": "Quick",
        "points": 2
      },
      {
        "id": 52,
        "control": true,
        "type": "Cheat",
        "points": 2
      },
      {
        "id": 52,
        "control": false,
        "type": "Favorite",
        "points": 2
      },
      {
        "id": 53,
        "control": true,
        "type": "Agile",
        "points": 2
      },
      {
        "id": 53,
        "control": false,
        "type": "Heavy",
        "points": 3
      },
      {
        "id": 54,
        "control": false,
        "type": "Helped",
        "points": 2
      },
      {
        "id": 54,
        "control": true,
        "type": "Object",
        "points": 2
      },
      {
        "id": 55,
        "control": true,
        "type": "Specialty",
        "text": "Check wrestler's card."
      },
      {
        "id": 55,
        "control": false,
        "type": "Trailing",
        "points": "d6"
      },
      {
        "id": 56,
        "control": false,
        "type": "Ref Bump",
        "text": "Go to Highlight Reel \"K\"."
      },
      {
        "id": 56,
        "control": false,
        "type": "Test of Strength",
        "text": "If BOTH wrestlers are STRONG and/or POWERFUL, roll a die until ref break... 1-2 Face scores 1 point, 3-4 Ref breaks hold, 5-6 Heel scores 1 point"
      },
      {
        "id": 57,
        "control": false,
        "type": "Strong",
        "points": 1,
        "text": "Submission! Wrestler scores 1 point and additional point(s) until opponent breaks hold with a die roll of 1-3. (Strong opponent, 1-4)"
      },
      {
        "id": 57,
        "control": false,
        "type": "Trailing",
        "points": 2
      },
      {
        "id": 58,
        "control": false,
        "type": "Agile",
        "points": 1,
        "text": "Submission! Wrestler scores 1 point and additional point(s) until opponent breaks hold with a die roll of 1-3. (Strong opponent, 1-4)"
      },
      {
        "id": 58,
        "control": false,
        "type": "Trailing",
        "points": 2
      },
      {
        "id": 59,
        "control": false,
        "type": "Mean",
        "points": 1,
        "text": "Submission! Wrestler scores 1 point and additional point(s) until opponent breaks hold with a die roll of 1-3. (Strong opponent, 1-4)"
      },
      {
        "id": 59,
        "control": false,
        "type": "Trailing",
        "points": 3
      },
      {
        "id": 60,
        "control": false,
        "type": "Powerful",
        "points": 1,
        "text": "Submission! Wrestler scores 1 point and additional point(s) until opponent breaks hold with a die roll of 1-3. (Strong opponent, 1-4)"
      },
      {
        "id": 60,
        "control": false,
        "type": "Trailing",
        "points": 3
      }
    ]
}